{"table":
[
	{"cols":["aufmerksam","attentive","Er ist immer sehr aufmerksam zu älteren Menschen."]},
	{"cols":["fröhlich","cheerful","Petra ist meistens sehr fröhlich und hat gute Laune."]},
	{"cols":["lieb","dear,kind","Das ist sehr lieb von dir, mir zu helfen."]},
	{"cols":["flexibel","flexible","Ich habe flexible Arbeitszeiten."]},
	{"cols":["freundlich","friendly","Unsere Sekretärin ist zu Studenten sehr freundlich."]},
	{"cols":["grosszügig","generous","Mein nkel war sehr grosszügig. Er hat mir den Flug nach Bogota bezahlt."]},
	{"cols":["froh","happy","Wir wünschen Ihnen frohe Weihnachten."]},
	{"cols":["hilflos","helpless","Ohne Rollstuhl ist Tom ziemlich hilflos."]},
	{"cols":["ehrlich","honest","Ein ehrlicher Mensch sagt meistens, was er denkt."]},
	{"cols":["menschlich","human","Mein hef ist sehr menschlich."]},
	{"cols":["bescheiden","modest","Unser rofessor ist sehr bescheiden."]},
	{"cols":["nett","nice","Der neue Freund von Erica ist sehr nett."]},
	{"cols":["offen","open","Petra ist immer offen für neues."]},
	{"cols":["stolz","proud","Wir sind sehr stolz auf dich."]},
	{"cols":["ruhig","quiet, calm","Auch bei roblemen bleibt er immer ruhig."]},
	{"cols":["ernst","serious","Ren ist sehr lustig, nur bei der Arbeit ist er ernst."]},
	{"cols":["komisch","strange, funny","Er sieht komisch aus, ist aber sonst sehr nett."]},
	{"cols":["streng","strict","Unsere Lehrerin ist sehr streng."]},
	{"cols":["blöd","stupid","Sie fand Thomas ziemlich blöd."]},
	{"cols":["typisch","typical","Man erkennt sie sofort an ihrem typischen Lachen."]},
	{"cols":["der Wille","will","Als rofisportler braucht man einen starken Willen."]},
	{"cols":["der charakter","character","Meine Schwester hat einen guten charakter."]},
	{"cols":["die Intelligenz","intelligence","Mit Intelligenz geht vieles einfacher im Leben."]},
	{"cols":["die Geduld","patience","Ich möchte mich für Ihre Geduld bedanken."]},
	{"cols":["die Unsicherheit","uncertainty","Seine Unsicherheit zeigt sich in seiner Verhaltensweise."]},
	{"cols":["die Verhaltensweise","behaviour","Er studiert die Verhaltensweisen von Tigern"]},
	{"cols":["treu","faithful","Annemarie ist meine treueste Freundin."]},
	{"cols":["sorgfältig","careful","Sie hat sehr sorgfältig und genau gearbeitet."]},
	{"cols":["neugierig","curious","Ich bin neugierig auf die neue Freundin von ochen."]},
	{"cols":["vernünftig","reasonable","Es wäre vernünftig, jetzt nach Hause zu gehen."]},
	{"cols":["klug","clever","Er ist ein ziemlich kluger Kopf."]},
	{"cols":["dumm","stupid","Es war eine dumme Entscheidung."]},
	{"cols":["lustig","funny","Es war ein lustiger Abend."]},
	{"cols":["nachdenklich","thougtful","Die momentane politische Lage macht mich nachdenklich."]},
	{"cols":["moralisch","moral","Moralisch ist diese Entscheidung nicht zu vertreten."]},
	{"cols":["optimistisch","optimistic","Insgesamt bin ich sehr optimistisch"]},
	{"cols":["empfindlich","sensitive","Peter reagiert empfindlich auf Kälte."]},
	{"cols":["zuverlässig","reliable","Petra arbeitet sehr schnell und zuverlässig."]},
	{"cols":["konsequent","consistent, consequent","In allem, was sie tut, ist sie sehr konsequent"]}
]}
